LICENSE
README.md
setup.cfg
setup.py
mantra_voice/__init__.py
mantra_voice/exceptions.py
mantra_voice/tts.py
mantra_voice.egg-info/PKG-INFO
mantra_voice.egg-info/SOURCES.txt
mantra_voice.egg-info/dependency_links.txt
mantra_voice.egg-info/requires.txt
mantra_voice.egg-info/top_level.txt