Metadata-Version: 2.1
Name: mantra-voice
Version: 0.4
Summary: A speech to text library that builds on top of gTTS and pyttsx3.
Home-page: https://github.com/bossauh/mantra-voice
Author: Philippe Mathew
Author-email: philmattdev@gmail.com
License: MIT
Download-URL: https://github.com/bossauh/mantra-voice/archive/refs/tags/v_04.tar.gz
Keywords: speech,synthesizer
Platform: UNKNOWN
Classifier: Development Status :: 4 - Beta
Classifier: Intended Audience :: Developers
Classifier: Topic :: Software Development :: Build Tools
Classifier: License :: OSI Approved :: MIT License
Classifier: Programming Language :: Python :: 3.6
Classifier: Programming Language :: Python :: 3.7
License-File: LICENSE
